pyssembly.py
pyssembly-1.0.5.dist-info/METADATA
pyssembly-1.0.5.dist-info/WHEEL
pyssembly-1.0.5.dist-info/top_level.txt
pyssembly-1.0.5.dist-info/RECORD
