Metadata-Version: 2.1
Name: pyssembly
Version: 1.0.5
Summary: Pyssembly allows to execute pseudo assembly code and it is meant for teaching purposes.
Home-page: https://github.com/GabrieleMaurina/pyssembly
Author: Gabriele Maurina
Author-email: gabrielemaurina95@gmail.com
License: MIT
Platform: UNKNOWN
Classifier: Programming Language :: Python :: 3
Classifier: License :: OSI Approved :: MIT License
Classifier: Operating System :: OS Independent
Requires-Python: >=3.8
